onepi/__init__.py
onepi/one.py
onepi/requirements.txt
onepi/development_tools/find_max_motor_rpm.py
onepi/development_tools/find_pulses_per_rev.py
onepi/development_tools/joystick_track_pose_rpm.py
onepi/development_tools/shapes_sim.py
onepi/development_tools/tune_PIC_PID.py
onepi/diagnostics/__init__.py
onepi/diagnostics/line_detection.png
onepi/diagnostics/plot_line_sensor.py
onepi/diagnostics/simulate_gaussian.py
onepi/examples/__init__.py
onepi/examples/advanced/__init__.py
onepi/examples/advanced/crazy_race_basic.py
onepi/examples/advanced/draw_shapes.py
onepi/examples/advanced/encoders.py
onepi/examples/advanced/ir_sensors.py
onepi/examples/advanced/motors_rpm.py
onepi/examples/advanced/motors_rpm_encoders.py
onepi/examples/advanced/start_race_detection.py
onepi/examples/basic/__init__.py
onepi/examples/basic/battery.py
onepi/examples/basic/buzzer.py
onepi/examples/basic/lcd.py
onepi/examples/basic/led.py
onepi/examples/basic/motors.py
onepi/examples/basic/pitches.py
onepi/examples/basic/push_buttons.py
onepi/examples/basic/welcome.py
onepi/examples/calibrate/compass_calibrate.py
onepi/examples/calibrate/config_speed_factor.json
onepi/examples/calibrate/line_sensor_calibrate.py
onepi/examples/calibrate/motors_calibrate.py
onepi/examples/crazy_race/crazy_race_basic.py
onepi/examples/extra/__init__.py
onepi/examples/extra/compass_read.py
onepi/examples/extra/servos.py
onepi/examples/extra/sonar.py
onepi/examples/fun_challenge/__init__.py
onepi/examples/fun_challenge/fun_challenge_delays.py
onepi/examples/fun_challenge/fun_challenge_state_machine.py
onepi/examples/line_sensor/01_sensor_read.py
onepi/examples/line_sensor/02_line_follow.py
onepi/examples/line_sensor/03_1_line_read_weight.py
onepi/examples/line_sensor/03_2_line_follow_weight.py
onepi/examples/line_sensor/03_3_line_follow_weight_lin.py
onepi/examples/line_sensor/04_2_line_read_linear.py
onepi/examples/line_sensor/04_3_line_follow_linear.py
onepi/examples/line_sensor/04_4_line_follow_cosine.py
onepi-1.1.3.dist-info/LICENSE
onepi-1.1.3.dist-info/METADATA
onepi-1.1.3.dist-info/WHEEL
onepi-1.1.3.dist-info/top_level.txt
onepi-1.1.3.dist-info/RECORD
