Metadata-Version: 2.2
Name: onepi
Version: 1.1.3
Summary: Python library to interface with Bot'n Roll One A+
Home-page: https://github.com/botnroll/bnronepi
Author: Bot'n Roll
Author-email: botnroll@botnroll.com
License: MIT
Classifier: Development Status :: 3 - Alpha
Classifier: Intended Audience :: Developers
Classifier: License :: OSI Approved :: MIT License
Classifier: Programming Language :: Python :: 3
Classifier: Programming Language :: Python :: 3.6
Classifier: Programming Language :: Python :: 3.7
Classifier: Programming Language :: Python :: 3.8
Classifier: Programming Language :: Python :: 3.9
Classifier: Programming Language :: Python :: 3.10
Classifier: Programming Language :: Python :: 3.11
License-File: LICENSE
Requires-Dist: spidev
Requires-Dist: matplotlib
Requires-Dist: rpi-lgpio
Requires-Dist: setproctitle
Dynamic: author
Dynamic: author-email
Dynamic: classifier
Dynamic: description
Dynamic: description-content-type
Dynamic: home-page
Dynamic: license
Dynamic: requires-dist
Dynamic: summary
